formancesdkwallets/__init__.py
formancesdkwallets/balances.py
formancesdkwallets/holds.py
formancesdkwallets/sdk.py
formancesdkwallets/sdkconfiguration.py
formancesdkwallets/wallets.py
formancesdkwallets/_hooks/__init__.py
formancesdkwallets/_hooks/clientcredentials.py
formancesdkwallets/_hooks/registration.py
formancesdkwallets/_hooks/sdkhooks.py
formancesdkwallets/_hooks/types.py
formancesdkwallets/models/__init__.py
formancesdkwallets/models/components/__init__.py
formancesdkwallets/models/components/balance.py
formancesdkwallets/models/components/balanceswithassets.py
formancesdkwallets/models/components/creditwalletinput.py
formancesdkwallets/models/components/debitwalletinput.py
formancesdkwallets/models/components/hold.py
formancesdkwallets/models/components/schemeformanceoauth.py
formancesdkwallets/models/components/security.py
formancesdkwallets/models/components/serverinfo.py
formancesdkwallets/models/components/wallet.py
formancesdkwallets/models/components/walletcounterpart.py
formancesdkwallets/models/components/walletcounterpartaccount.py
formancesdkwallets/models/components/walletcounterpartwallet.py
formancesdkwallets/models/components/walletserrorcodes.py
formancesdkwallets/models/components/walletsummary.py
formancesdkwallets/models/errors/__init__.py
formancesdkwallets/models/errors/sdkerror.py
formancesdkwallets/models/errors/walletserror.py
formancesdkwallets/models/operations/__init__.py
formancesdkwallets/models/operations/balances_create.py
formancesdkwallets/models/operations/balances_get.py
formancesdkwallets/models/operations/balances_list.py
formancesdkwallets/models/operations/holds_cancel.py
formancesdkwallets/models/operations/holds_confirm.py
formancesdkwallets/models/operations/holds_get.py
formancesdkwallets/models/operations/holds_list.py
formancesdkwallets/models/operations/wallets_create.py
formancesdkwallets/models/operations/wallets_credit.py
formancesdkwallets/models/operations/wallets_debit.py
formance_sdk_wallets-0.2.1.dist-info/METADATA
formance_sdk_wallets-0.2.1.dist-info/WHEEL
formance_sdk_wallets-0.2.1.dist-info/top_level.txt
formance_sdk_wallets-0.2.1.dist-info/RECORD
